Curso_DDA/unit1/Ejercicios/d_ff.v
module d_ff #(
    parameter BITS = 8,
    parameter DEBUG = 0
)(
    input      [BITS-1:0]   i_Din,
    input                   i_clk,
    input                   i_rst,
    output reg [BITS-1:0]   o_Dout
);

always @(posedge i_clk or negedge i_rst) begin
    $display("Flop %4d | i_Din %4d | o_Dout %4d | i_rst %4d", DEBUG, i_Din, o_Dout, i_rst);
    if (!i_rst) begin
        // $display("reinicio flop %2d", DEBUG);
        o_Dout <= { BITS{1'b0} };
    end
    else begin
        // $display("Flop %2d: input %2d -> output %2d", DEBUG, i_Din, o_Dout);
        o_Dout <= i_Din;
    end
end

endmodule

Curso_DDA/unit1/Ejercicios/data_delay.v
`include "d_ff.v"

module data_delay #(
    parameter DELAY = 4,    // Cantidad de ciclos de retardo
    parameter BITS = 8     // Tamaño de los datos a retardar
)(
    input                   i_clk,
    input                   i_rst,
    input       [BITS-1:0]  i_Din,  // Palabra a la entrada
    //output reg  [DELAY-1:0] [BITS-1:0]  o_Dout // Tengo una palabra por cada ciclo de retardo (Para IC)
    output reg  [(DELAY * BITS)-1:0]  o_Dout // Tengo una palabra por cada ciclo de retardo (Para FPGA)
);

    wire [(DELAY * BITS)-1:0] data_scale;

    assign o_Dout = data_scale;

    genvar index;
    generate
        for (index = 0; index <= DELAY-1; index = index + 1) begin
            if (index == 0) begin
                d_ff #(
                    .BITS(BITS),
                    .DEBUG(0)
                ) u_dff (
                    .i_Din(i_Din),
                    .i_clk(i_clk),
                    .i_rst(i_rst),
                    // .o_Dout(o_Dout[index])  // Para IC
                    .o_Dout(data_scale[BITS-1:0])  // Para FPGA
                );
            end
            else begin
                d_ff #(
                    .BITS(BITS),
                    .DEBUG(index)
                ) u_dff (
                    .i_Din(data_scale[index*BITS-1:(index-1)*BITS]),
                    .i_clk(i_clk),
                    .i_rst(i_rst),
                    // .o_Dout(o_Dout[index])  // Para IC
                    .o_Dout(data_scale[(index+1)*BITS-1:index*BITS])  // Para FPGA
                    );               
            end
        end
    endgenerate

endmodule

Curso_DDA/unit1/Ejercicios/data_delay_tb.v
`timescale 100ns/1ns
`include "data_delay.v"
`define BITS 8
`define DELAY 4

module data_delay_tb;
    
    reg i_clk;
    reg i_rst;
    reg [`BITS-1:0] i_Din;
    // reg [`DELAY-1:0] [`BITS-1:0] o_Dout; // Para IC
    reg [(`DELAY * `BITS)-1:0] o_Dout;  // Para FPGA

    data_delay #(
        .DELAY(`DELAY),
        .BITS(`BITS)
    ) uut (
        .i_Din(i_Din),
        .i_clk(i_clk),
        .i_rst(i_rst),
        .o_Dout(o_Dout)
    );

    initial begin
        // Se configuran los archivos en donde se imprimen las señales
        $dumpfile("data_delay_tb.vcd");
        $dumpvars(4, data_delay_tb);
        // $monitor("Din: %d | Dout0: %d| Dout1: %d| Dout2: %d| Dout3: %d", i_Din, o_Dout[0], o_Dout[1], o_Dout[2], o_Dout[3]); // Para IC
        // $monitor("Din: %d | Dout0: %d| Dout1: %d| Dout2: %d| Dout3: %d", i_Din, o_Dout[`BITS-1:0], o_Dout[2*`BITS-1:`BITS], o_Dout[3*`BITS-1:2*`BITS], o_Dout[4*`BITS-1:3*`BITS]);  // Para FPGA
        $monitor("Din: %4d | Dout: %4d | data_scale: %4d\n", i_Din, o_Dout, uut.data_scale);  // Para FPGA

        i_clk = 0;
        i_rst = 0;    // Llevo el sistema a un estado conocido
    end

    always #1 i_clk = !i_clk;

    always @(posedge i_clk) begin
        if ($time > 3) begin
            i_rst = 1;
        end
        if ($time > 13) begin
            $finish;
        end
        i_Din = $random%(2**`BITS);
    end

endmodule

Curso_DDA/unit1/Ejercicios/data_delay_tb.vcd
$date
	Tue Dec 21 18:47:01 2021
$end
$version
	Icarus Verilog
$end
$timescale
	1ns
$end
$scope module data_delay_tb $end
$var wire 32 ! o_Dout [31:0] $end
$var reg 8 " i_Din [7:0] $end
$var reg 1 # i_clk $end
$var reg 1 $ i_rst $end
$scope module uut $end
$var wire 8 % i_Din [7:0] $end
$var wire 1 # i_clk $end
$var wire 1 $ i_rst $end
$var wire 32 & o_Dout [31:0] $end
$var wire 32 ' data_scale [31:0] $end
$scope begin genblk1[0] $end
$scope begin genblk2 $end
$upscope $end
$upscope $end
$scope begin genblk1[1] $end
$scope begin genblk3 $end
$upscope $end
$upscope $end
$scope begin genblk1[2] $end
$scope begin genblk3 $end
$upscope $end
$upscope $end
$scope begin genblk1[3] $end
$scope begin genblk3 $end
$upscope $end
$upscope $end
$upscope $end
$upscope $end
$enddefinitions $end
#0
$dumpvars
b0 '
b0 &
bx %
0$
0#
bx "
b0 !
$end
#100
b100100 "
b100100 %
1#
#200
0#
#300
b10000001 "
b10000001 %
1#
#400
0#
#500
b1001 !
b1001 &
b1001 '
b1001 "
b1001 %
1$
1#
#600
0#
#700
b100101100011 !
b100101100011 &
b100101100011 '
b1100011 "
b1100011 %
1#
#800
0#
#900
b10010110001100001101 !
b10010110001100001101 &
b10010110001100001101 '
b1101 "
b1101 %
1#
#1000
0#
#1100
b1001011000110000110110001101 !
b1001011000110000110110001101 &
b1001011000110000110110001101 '
b10001101 "
b10001101 %
1#
#1200
0#
#1300
b1100011000011011000110101100101 !
b1100011000011011000110101100101 &
b1100011000011011000110101100101 '
b1100101 "
b1100101 %
1#
