Curso_DDA/unit1/Ejercicios/d_ff.v
module d_ff #(
    parameter BITS = 8
)(
    input      [BITS-1:0]   i_Din,
    input                   i_clk,
    input                   i_rst,
    output reg [BITS-1:0]   o_Dout
);

always @(posedge i_clk or negedge i_rst) begin
    if (!i_rst) begin
        o_Dout <= { BITS{1'b0} };
    end
    else begin
        o_Dout <= i_Din;
    end
end

endmodule

Curso_DDA/unit1/Ejercicios/data_delay.v
`include "d_ff.v"

module data_delay #(
    parameter DELAY = 4,    // Cantidad de ciclos de retardo
    parameter BITS = 8     // Tamaño de los datos a retardar
)(
    input                   i_clk,
    input                   i_rst,
    input       [BITS-1:0]  i_Din,  // Palabra a la entrada
    output reg  [DELAY-1:0] [BITS-1:0]  o_Dout // Tengo una palabra por cada ciclo de retardo
);

    genvar index;
    generate
        for (index = 0; index < DELAY; index = index + 1) begin
            if (index == 0) begin
                d_ff #(.BITS(BITS)) u_dff (
                    .i_Din(i_Din),
                    .i_clk(i_clk),
                    .i_rst(i_rst),
                    .o_Dout(o_Dout[index])
                );
            end
            else begin
                d_ff #(.BITS(BITS)) u_dff (
                    .i_Din(o_Dout[index-1]),
                    .i_clk(i_clk),
                    .i_rst(i_rst),
                    .o_Dout(o_Dout[index])
                    );               
            end
        end
    endgenerate

endmodule

Curso_DDA/unit1/Ejercicios/data_delay_tb.v
`timescale 1ns/1ps
`include "data_delay.v"
`define BITS 16
`define DELAY 4

module data_delay_tb;
    
    reg i_clk;
    reg i_rst;
    reg [`BITS-1:0] i_Din;
    reg [`DELAY-1:0] [`BITS-1:0] o_Dout;

    data_delay #(
        .DELAY(`DELAY),
        .BITS(`BITS)
    ) uut (
        .i_Din(i_Din),
        .i_clk(i_clk),
        .i_rst(i_rst),
        .o_Dout(o_Dout)
    );

    initial begin
        // Se configuran los archivos en donde se imprimen las señales
        $dumpfile("data_delay_tb.vcd");
        $dumpvars(0, data_delay_tb);
        $monitor("Din: %d | Dout0: %d| Dout1: %d| Dout2: %d| Dout3: %d", i_Din, o_Dout[0], o_Dout[1], o_Dout[2], o_Dout[3]);

        i_clk = 0;
        i_rst = 0;    // Llevo el sistema a un estado conocido
    end

    always #1 i_clk = !i_clk;

    always @(posedge i_clk) begin
        if ($time > 3) begin
            i_rst = 1;
        end
        if ($time > 13) begin
            $finish;
        end
        i_Din = $random%(2**`BITS);
    end

endmodule

Curso_DDA/unit1/Ejercicios/data_delay_tb.vcd
$date
	Sun Sep 19 20:58:52 2021
$end
$version
	Icarus Verilog
$end
$timescale
	1ps
$end
$scope module data_delay_tb $end
$var wire 64 ! o_Dout [63:0] $end
$var reg 16 " i_Din [15:0] $end
$var reg 1 # i_clk $end
$var reg 1 $ i_rst $end
$scope module uut $end
$var wire 16 % i_Din [15:0] $end
$var wire 1 # i_clk $end
$var wire 1 $ i_rst $end
$var wire 64 & o_Dout [63:0] $end
$scope begin genblk1[0] $end
$scope begin genblk2 $end
$scope module u_dff $end
$var wire 16 ' i_Din [15:0] $end
$var wire 1 # i_clk $end
$var wire 1 $ i_rst $end
$var reg 16 ( o_Dout [15:0] $end
$upscope $end
$upscope $end
$upscope $end
$scope begin genblk1[1] $end
$scope begin genblk3 $end
$scope module u_dff $end
$var wire 16 ) i_Din [15:0] $end
$var wire 1 # i_clk $end
$var wire 1 $ i_rst $end
$var reg 16 * o_Dout [15:0] $end
$upscope $end
$upscope $end
$upscope $end
$scope begin genblk1[2] $end
$scope begin genblk3 $end
$scope module u_dff $end
$var wire 16 + i_Din [15:0] $end
$var wire 1 # i_clk $end
$var wire 1 $ i_rst $end
$var reg 16 , o_Dout [15:0] $end
$upscope $end
$upscope $end
$upscope $end
$scope begin genblk1[3] $end
$scope begin genblk3 $end
$scope module u_dff $end
$var wire 16 - i_Din [15:0] $end
$var wire 1 # i_clk $end
$var wire 1 $ i_rst $end
$var reg 16 . o_Dout [15:0] $end
$upscope $end
$upscope $end
$upscope $end
$upscope $end
$upscope $end
$enddefinitions $end
#0
$dumpvars
b0 .
b0 -
b0 ,
b0 +
b0 *
b0 )
b0 (
bx '
b0 &
bx %
0$
0#
bx "
b0 !
$end
#1000
b11010100100100 "
b11010100100100 %
b11010100100100 '
1#
#2000
0#
#3000
b101111010000001 "
b101111010000001 %
b101111010000001 '
1#
#4000
0#
#5000
b1101011000001001 )
b1101011000001001 !
b1101011000001001 &
b1101011000001001 (
b1101011000001001 "
b1101011000001001 %
b1101011000001001 '
1$
1#
#6000
0#
#7000
b101011001100011 )
b1101011000001001 +
b101011001100011 (
b11010110000010010101011001100011 !
b11010110000010010101011001100011 &
b1101011000001001 *
b101011001100011 "
b101011001100011 %
b101011001100011 '
1#
#8000
0#
#9000
b1101011000001001 -
b101011001100011 +
b111101100001101 )
b1101011000001001 ,
b101011001100011 *
b110101100000100101010110011000110111101100001101 !
b110101100000100101010110011000110111101100001101 &
b111101100001101 (
b111101100001101 "
b111101100001101 %
b111101100001101 '
1#
#10000
0#
#11000
b1001100110001101 )
b111101100001101 +
b101011001100011 -
b1001100110001101 (
b111101100001101 *
b101011001100011 ,
b1101011000001001010101100110001101111011000011011001100110001101 !
b1101011000001001010101100110001101111011000011011001100110001101 &
b1101011000001001 .
b1001100110001101 "
b1001100110001101 %
b1001100110001101 '
1#
#12000
0#
#13000
b111101100001101 -
b1001100110001101 +
b1000010001100101 )
b101011001100011 .
b111101100001101 ,
b1001100110001101 *
b101011001100011011110110000110110011001100011011000010001100101 !
b101011001100011011110110000110110011001100011011000010001100101 &
b1000010001100101 (
b1000010001100101 "
b1000010001100101 %
b1000010001100101 '
1#
#14000
0#
#15000
b1000010001100101 +
b1001100110001101 -
b1000010001100101 *
b1001100110001101 ,
b111101100001101100110011000110110000100011001011000010001100101 !
b111101100001101100110011000110110000100011001011000010001100101 &
b111101100001101 .
1#
