Curso_DDA/unit1/Ejercicios/Ejercicio2.v
module ejercicio2 
#(
    parameter bits = 4
)
(
    input       [bits-1:0]  i_dataA,
    input       [bits-1:0]  i_dataB,
    output reg  [bits-1:0]  o_dataC,
    input       [1:0]       i_sel
);

    always @(*) begin
        case (i_sel)
            0: begin
                o_dataC = i_dataA + i_dataB;
            end
            1: begin
                o_dataC = i_dataA - i_dataB;                
            end
            2: begin
                o_dataC = i_dataA & i_dataB;                
            end
            3: begin
                o_dataC = i_dataA | i_dataB;                
            end
            default: begin
                o_dataC = {bits{1'bz}};
            end
        endcase
    end

endmodule

Curso_DDA/2021/unit1/Ejercicios/Ejercicio2_tb.v
`timescale 1ns/1ps
`include "Ejercicio2.v"

`define BITS 4

module Ejercicio2_tb;

    reg [`BITS-1:0] data1;
    reg [`BITS-1:0] data2;
    reg [1:0] sel;

    wire [`BITS-1:0] data_out;

    ejercicio2 #(
        .bits(`BITS)
    ) uut (
        .i_dataA(data1),
        .i_dataB(data2),
        .i_sel(sel),
        .o_dataC(data_out)
    );

    initial begin
        // Se configuran los archivos en donde se imprimen las señales
        $dumpfile("Ejercicio2_tb.vcd");
        $dumpvars(0, Ejercicio2_tb);

        $monitor("[%g] dataA: %d | dataB: %d | sel: %d | out: %d", $time, data1, data2, sel, data_out);
        data1 = $random%( 2**`BITS ); data2 = $random%( 2**`BITS ); sel = 0;
        #1;
        data1 = $random%( 2**`BITS ); data2 = $random%( 2**`BITS ); sel = 0;
        #1;
        data1 = $random%( 2**`BITS ); data2 = $random%( 2**`BITS ); sel = 1;
        #1;
        data1 = $random%( 2**`BITS ); data2 = $random%( 2**`BITS ); sel = 1;
        #1;

        $monitor("[%g] dataA: 0x%b | dataB: 0x%b | sel: %d | out: 0x%b", $time, data1, data2, sel, data_out);
        data1 = $random%( 2**`BITS ); data2 = $random%( 2**`BITS ); sel = 2;
        #1;
        data1 = $random%( 2**`BITS ); data2 = $random%( 2**`BITS ); sel = 2;
        #1;
        data1 = $random%( 2**`BITS ); data2 = $random%( 2**`BITS ); sel = 3;
        #1;
        data1 = $random%( 2**`BITS ); data2 = $random%( 2**`BITS ); sel = 3;
        #1;

        $finish;
    end

endmodule

Curso_DDA/unit1/Ejercicios/Ejercicio2_tb.vcd
$date
	Fri Sep 10 03:21:16 2021
$end
$version
	Icarus Verilog
$end
$timescale
	1ps
$end
$scope module Ejercicio2_tb $end
$var wire 4 ! data_out [3:0] $end
$var reg 4 " data1 [3:0] $end
$var reg 4 # data2 [3:0] $end
$var reg 2 $ sel [1:0] $end
$scope module uut $end
$var wire 4 % i_dataA [3:0] $end
$var wire 4 & i_dataB [3:0] $end
$var wire 2 ' i_sel [1:0] $end
$var reg 4 ( o_dataC [3:0] $end
$upscope $end
$upscope $end
$enddefinitions $end
#0
$dumpvars
b101 (
b0 '
b1 &
b100 %
b0 $
b1 #
b100 "
b101 !
$end
#1000
b1100 !
b1100 (
b11 #
b11 &
b1001 "
b1001 %
#2000
b0 !
b0 (
b1 $
b1 '
b1101 #
b1101 &
b1101 "
b1101 %
#3000
b11 !
b11 (
b10 #
b10 &
b101 "
b101 %
#4000
b1 !
b1 (
b10 $
b10 '
b1101 #
b1101 &
b1 "
b1 %
#5000
b100 !
b100 (
b110 "
b110 %
#6000
b1101 !
b1101 (
b11 $
b11 '
b1100 #
b1100 &
b1101 "
b1101 %
#7000
b1111 !
b1111 (
b110 #
b110 &
b1001 "
b1001 %
