Curso_DDA/2021/unit1/Ejercicios/pow_2_divider.v
module pow_2_divider #(
    parameter BITS = 8,
    parameter DIVIDE = 4
)(
    input      [BITS-1:0]   i_Din,
    input                   i_clk,
    output reg [BITS-1:0]   o_Dout
);

always @(posedge i_clk) begin
    // o_Dout = { { $clog2(DIVIDE){1'b0} } , i_Din[BITS-1:$clog2(DIVIDE)] };
    $display("time: %4d | Din: %4b (%4d) | Dout: %4b (%4d) | pre-divider", $time, i_Din, i_Din, o_Dout, o_Dout);  // Para FPGA
    o_Dout = i_Din>>$clog2(DIVIDE);
    $display("time: %4d | Din: %4b (%4d) | Dout: %4b (%4d) | post-divider", $time, i_Din, i_Din, o_Dout, o_Dout);  // Para FPGA
end

endmodule

Curso_DDA/unit1/Ejercicios/pow_2_divider_tb.v
`timescale 100ns/1ns
`include "pow_2_divider.v"
`define BITS 8
`define DIVIDE 4

module pow_2_divider_tb;
    
    reg i_clk;
    reg [`BITS-1:0] i_Din;
    // reg [`BITS-1:0] o_Dout; // Para IC
    reg [`BITS-1:0] o_Dout;  // Para FPGA

    pow_2_divider #(
        .DIVIDE(`DIVIDE),
        .BITS(`BITS)
    ) uut (
        .i_Din(i_Din),
        .i_clk(i_clk),
        .o_Dout(o_Dout)
    );

    initial begin
        // Se configuran los archivos en donde se imprimen las señales
        $dumpfile("pow_2_divider_tb.vcd");
        $dumpvars(2, pow_2_divider_tb);
        $monitor("time: %4d | Din: %4b (%4d) | Dout: %4b (%4d) | testbench", $time, i_Din, i_Din, o_Dout, o_Dout);  // Para FPGA

        i_clk = 0;
        i_Din = 0;
    end

    always #2 i_clk = !i_clk;

    always @(posedge i_clk) begin
        if ($time > 34) begin
            $finish;
        end
        if ($time%2 == 0) begin
            i_Din <= $random%(2**`BITS);
        end
    end

endmodule

Curso_DDA/unit1/Ejercicios/pow_2_divider_tb.vcd
$date
	Tue Dec 21 19:39:13 2021
$end
$version
	Icarus Verilog
$end
$timescale
	1ns
$end
$scope module pow_2_divider_tb $end
$var wire 8 ! o_Dout [7:0] $end
$var reg 8 " i_Din [7:0] $end
$var reg 1 # i_clk $end
$scope module uut $end
$var wire 8 $ i_Din [7:0] $end
$var wire 1 # i_clk $end
$var reg 8 % o_Dout [7:0] $end
$upscope $end
$upscope $end
$enddefinitions $end
#0
$dumpvars
bx %
b0 $
0#
b0 "
bx !
$end
#200
b100100 "
b100100 $
b0 !
b0 %
1#
#400
0#
#600
b10000001 "
b10000001 $
b1001 !
b1001 %
1#
#800
0#
#1000
b1001 "
b1001 $
b100000 !
b100000 %
1#
#1200
0#
#1400
b1100011 "
b1100011 $
b10 !
b10 %
1#
#1600
0#
#1800
b1101 "
b1101 $
b11000 !
b11000 %
1#
#2000
0#
#2200
b10001101 "
b10001101 $
b11 !
b11 %
1#
#2400
0#
#2600
b1100101 "
b1100101 $
b100011 !
b100011 %
1#
#2800
0#
#3000
b10010 "
b10010 $
b11001 !
b11001 %
1#
#3200
0#
#3400
b1 "
b1 $
b100 !
b100 %
1#
#3600
0#
#3800
b0 !
b0 %
1#
