fifo_mem/fifo_mem.v
module fifo_counter #(
    parameter depth = 8 // defino la profundidad del fifo que maneja
)
(
    clk,            //  Senal de reloj
    push,           //  Indica que entra un registro
    pop,            //  Indica que sale un registro
    full,           //  Indica que la memoria esta llena
    pndng,          //  Indica que hay datos sin leer
    pointer_in,     //  Puntero a donde guardar
    pointer_out,    //  Puntero a donde leer
    rst
);
    // Señales de entrada
    input clk, push, pop, rst;

    // Señales de salida
    output full, pndng;
    output reg[$clog2(depth)-1:0] pointer_out;  // Indica la posicion a leer datos

    //  Señales internas
    reg [$clog2(depth)-1:0] count;  // Indica la cantidad de registros en el FIFO

    // Defino dos maquinas de estado, una para el pointer in y otra para el pointer out
    output reg [$clog2(depth)-1:0] pointer_in;  // El estado es la posicion a guardar
    reg [$clog2(depth)-1:0] state_in;  // El estado es la posicion a guardar
    reg [$clog2(depth)-1:0] nxt_state_in;  // El estado es la posicion a guardar

    wire c;

    // Logica de siguiente estado
    //addern #(.bits(depth)) nxt_state_gen (.carryin(push), .A(state_in), .B('b0), .carryout(c), .Sum(nxt_state_in));

    // Aplico el cambio de estado
    always @(posedge clk or negedge rst) begin
        if (~rst) state_in <= 0;
        else begin
            state_in = nxt_state_in;
        end
    end

    // Logica de salida
    // Al ser una maquina de Moore, la salida depende del estado
    assign pointer_in = state_in;

endmodule

module demuxnm #(
    parameter bits = 8,     // Parametro para largo del registro
    parameter depth = 4     // Parametro para cantidad de registros
)
(
    ctrl,   // Entradas de control
    in_n,   // Entrada de N Bits
    out_nm  // M salidas de N bits
);
    input [$clog2(depth)-1:0] ctrl;         // Si tengo demux DEPTH señales preciso Log_2(DEPTH) bits de control
    input [bits-1:0] in_n;
    output [depth-1:0] [bits-1:0] out_nm ;

    // Instancio todas las salidas para mantener el control sobre estas todo el tiempo
    genvar index;
    generate
        for (index = 0; index < depth; index = index + 1) begin
            assign out_nm[index] = (ctrl == index)? in_n : 'bz;
        end
    endgenerate

endmodule

module muxnm #(
    parameter bits = 8,     // Parametro para largo del registro
    parameter depth = 4     // Parametro para cantidad de registros
)
(
    ctrl,   // Entradas de control
    in_nm,  // M entradas de N bits
    out_n   // Salida de N bits
);

    input [$clog2(depth)-1:0] ctrl; // Si debo demux DEPTH señales preciso Log_2(DEPTH) bits de control
    input [depth-1:0] [bits-1:0] in_nm ;
    output [bits-1:0] out_n;

    // A la salida tengo la entrada correspondiente al valor de ctrl
    assign out_n = in_nm[ctrl];

endmodule

// Arreglo de N Flip-Flops tipo D
module d_ff_n #(
    parameter bits = 8  // Parametro para largo del registro
)
(
    clk,      // Señal de clock
    Din_n,    // Datos de entrada de largo n
    Dout_n,   // Datos de salida de largo n
    clr
);
    input clk, clr;
    input [bits-1:0] Din_n;

    output reg [bits-1:0] Dout_n;

    always @(posedge clk or negedge clr) begin // Siempre que recibo un flanco de clk
        if (!clr) begin
            Dout_n <= 0;
        end
        else begin
            Dout_n <= Din_n;
        end
    end

endmodule

module fifo #(
    parameter bits = 8,
    parameter depth = 4
)
(
    clk,
    Din,
    Dout,
    push,
    pop,
    full,
    pndng,
    rst
);
    input clk, push, pop, rst;
    input [bits-1:0] Din;

    output full, pndng;
    output [bits-1:0] Dout;

    reg count;

    wire [$clog2(depth)-1:0] pointer_in;
    wire [$clog2(depth)-1:0] pointer_out;
    wire [bits-1:0] out_nm_mux [depth-1:0];
    wire [bits-1:0] in_nm_demux [depth-1:0];

    // fifo_counter #(depth) U1(
    //     .push(push), 
    //     .pop(pop), 
    //     .pointer_in(pointer_in), 
    //     .pointer_out(pointer_out), 
    //     .rst(rst), 
    //     .full(full), 
    //     .pndng(pndng)
    //     );
    // demuxnm #(bits, depth) U2(.ctrl(pointer_in), .in_n(Din), .out_nm(out_nm_mux));
    // d_ff_n #(bits) U3(.clk(clk), .Din_n(out_nm_mux), .Dout_n(in_nm_demux));
    // muxnm #(bits, depth) U4(.ctrl(pointer_out), .in_nm(in_nm_demux), .out_n(Dout));

endmodule

// Full-Adder
module fulladd (
    cin,    //  Carry-in
    a,      //  Bit a sumar
    b,      //  Bit a sumar
    s,      //  Suma de los bits
    cout    //  Carry-out
);
    input a, b, cin;
    output s, cout;

    // Se pueden asignar varias 'variables' separando cada asignacion con una coma en vez de punto-y-coma
    assign s = (a ^ b) ^ cin;
    assign cout = (b & cin) | (a & b) | (a & cin);

endmodule

// En este caso se instancia n-veces un modulo por medio del bloque 'generate'
// Cada instancia del modulo 'fulladd' sera renombrado addbit[k].stage
module addern #(
    parameter bits = 8  // Parametro para largo del registro
)
(
    carryin,    // Carry-in (1-bit)
    A,          // Vector/Numero a sumar
    B,          // Vector/Numero a sumar
    Sum,        // Suma de los vectores/numeros
    carryout    // Carry-out (1-bit)
);
    input carryin;
    input [bits-1:0] A;
    input [bits-1:0] B;

    output [bits-1:0] Sum;
    output carryout;
    
    wire [bits:0] C;    // Esta instancia sirve para unir los carrys. Tiene 1 bit mas que lo demas para el carry-out

    genvar i;   // Tipo de variable similar a integer, pero unicamente positivo y utilizable solo en bloques generate
    assign C[0] = carryin;
    assign carryout = C[bits];

    generate    // Aca instancio bit-a-bit cada sumador y realizo la suma del numero
        for (i = 0; i <= bits-1; i = i+1) begin:addbit    // Aca se renombra cada instancia
            fulladd stage (C[i], A[i], B[i], Sum[i], C[i+1]);
        end
    endgenerate

endmodule

fifo_mem/addern_tb.v
// Testbench for fifos multiplexer
`timescale 1ns/100ps
`default_nettype none
`define BITS    4
`include "fifo_mem.v"

module addern_tb;

    reg cin;
    reg [`BITS-1:0] A_number;
    reg [`BITS-1:0] B_number;
    wire [`BITS-1:0] Sum;
    wire cout;

    addern #(.bits(`BITS)) uut
    (
        .carryin(cin),    // Carry-in (1-bit)
        .A(A_number),          // Vector/Numero a sumar
        .B(B_number),          // Vector/Numero a sumar
        .Sum(Sum),        // Suma de los vectores/numeros
        .carryout(cout)    // Carry-out (1-bit)
    );

    initial begin

        $dumpfile("addern_tb.vcd");
        $dumpvars(2,uut);
        $monitor("(time: %1d) A=%d B=%d, Cin=%d, Sum=%d, Cout=%d", $time, A_number, B_number, cin, Sum, cout);
        // Inicializo las variables/Entradas
        A_number = {`BITS{1'b0}};
        B_number = {`BITS{1'b0}};
        cin = 1'b0;

    end

    always #1 A_number = A_number + { {`BITS-1{1'b0}} , 1'b1}; // Una forma un poco engorrosa pero parametrizable de sumar 1 de forma precisa
    always #(2**`BITS) B_number = B_number + { {`BITS-1{1'b0}} , 1'b1};
    always #(2**(2*`BITS)) $finish;

endmodule

fifo_mem/addern_tb.vcd
$date
	Wed Sep 01 00:24:14 2021
$end
$version
	Icarus Verilog
$end
$timescale
	100ps
$end
$scope module addern_tb $end
$scope module uut $end
$var wire 4 ! A [3:0] $end
$var wire 4 " B [3:0] $end
$var wire 1 # carryin $end
$var wire 1 $ carryout $end
$var wire 4 % Sum [3:0] $end
$var wire 5 & C [4:0] $end
$scope begin addbit[0] $end
$upscope $end
$scope begin addbit[1] $end
$upscope $end
$scope begin addbit[2] $end
$upscope $end
$scope begin addbit[3] $end
$upscope $end
$upscope $end
$upscope $end
$enddefinitions $end
#0
$dumpvars
b0 &
b0 %
0$
0#
b0 "
b0 !
$end
#10
b1 %
b1 !
#20
b10 %
b10 !
#30
b11 %
b11 !
#40
b100 %
b100 !
#50
b101 %
b101 !
#60
b110 %
b110 !
#70
b111 %
b111 !
#80
b1000 %
b1000 !
#90
b1001 %
b1001 !
#100
b1010 %
b1010 !
#110
b1011 %
b1011 !
#120
b1100 %
b1100 !
#130
b1101 %
b1101 !
#140
b1110 %
b1110 !
#150
b1111 %
b1111 !
#160
b1 %
b0 !
b1 "
#170
b10 &
b10 %
b1 !
#180
b11 %
b0 &
b10 !
#190
b110 &
b100 %
b11 !
#200
b101 %
b0 &
b100 !
#210
b10 &
b110 %
b101 !
#220
b111 %
b0 &
b110 !
#230
b1110 &
b1000 %
b111 !
#240
0$
b1001 %
b0 &
b1000 !
#250
b10 &
b1010 %
b1001 !
#260
b1011 %
b0 &
b1010 !
#270
b110 &
b1100 %
b1011 !
#280
0$
b1101 %
b0 &
b1100 !
#290
b10 &
b1110 %
b1101 !
#300
0$
b1111 %
b0 &
b1110 !
#310
1$
b11110 &
b0 %
b1111 !
#320
0$
b10 %
b0 &
b0 !
b10 "
#330
b11 %
b1 !
#340
b100 &
b100 %
b10 !
#350
b101 %
b11 !
#360
b110 %
b0 &
b100 !
#370
b111 %
b101 !
#380
b1100 &
b1000 %
b110 !
#390
b1001 %
b111 !
#400
0$
b1010 %
b0 &
b1000 !
#410
b1011 %
b1001 !
#420
b100 &
b1100 %
b1010 !
#430
b1101 %
b1011 !
#440
0$
b1110 %
b0 &
b1100 !
#450
b1111 %
b1101 !
#460
1$
b11100 &
b0 %
b1110 !
#470
b1 %
b1111 !
#480
0$
b11 %
b0 &
b0 !
b11 "
#490
b110 &
b100 %
b1 !
#500
b100 &
b101 %
b10 !
#510
b110 &
b110 %
b11 !
#520
b111 %
b0 &
b100 !
#530
b1110 &
b1000 %
b101 !
#540
b1100 &
b1001 %
b110 !
#550
b1110 &
b1010 %
b111 !
#560
0$
b1011 %
b0 &
b1000 !
#570
b110 &
b1100 %
b1001 !
#580
b100 &
b1101 %
b1010 !
#590
b110 &
b1110 %
b1011 !
#600
0$
b1111 %
b0 &
b1100 !
#610
1$
b11110 &
b0 %
b1101 !
#620
b11100 &
b1 %
b1110 !
#630
b11110 &
b10 %
b1111 !
#640
0$
b100 %
b0 &
b0 !
b100 "
#650
b101 %
b1 !
#660
b110 %
b10 !
#670
b111 %
b11 !
#680
b1000 &
b1000 %
b100 !
#690
b1001 %
b101 !
#700
b1010 %
b110 !
#710
b1011 %
b111 !
#720
0$
b1100 %
b0 &
b1000 !
#730
b1101 %
b1001 !
#740
b1110 %
b1010 !
#750
b1111 %
b1011 !
#760
1$
b11000 &
b0 %
b1100 !
#770
b1 %
b1101 !
#780
b10 %
b1110 !
#790
b11 %
b1111 !
#800
0$
b101 %
b0 &
b0 !
b101 "
#810
b10 &
b110 %
b1 !
#820
b111 %
b0 &
b10 !
#830
b1110 &
b1000 %
b11 !
#840
b1000 &
b1001 %
b100 !
#850
b1010 &
b1010 %
b101 !
#860
b1011 %
b1000 &
b110 !
#870
b1110 &
b1100 %
b111 !
#880
0$
b1101 %
b0 &
b1000 !
#890
b10 &
b1110 %
b1001 !
#900
0$
b1111 %
b0 &
b1010 !
#910
1$
b11110 &
b0 %
b1011 !
#920
b11000 &
b1 %
b1100 !
#930
b11010 &
b10 %
b1101 !
#940
b11 %
b11000 &
b1110 !
#950
b11110 &
b100 %
b1111 !
#960
0$
b110 %
b0 &
b0 !
b110 "
#970
b111 %
b1 !
#980
b1100 &
b1000 %
b10 !
#990
b1001 %
b11 !
#1000
b1000 &
b1010 %
b100 !
#1010
b1011 %
b101 !
#1020
b1100 &
b1100 %
b110 !
#1030
b1101 %
b111 !
#1040
0$
b1110 %
b0 &
b1000 !
#1050
b1111 %
b1001 !
#1060
1$
b11100 &
b0 %
b1010 !
#1070
b1 %
b1011 !
#1080
b11000 &
b10 %
b1100 !
#1090
b11 %
b1101 !
#1100
b11100 &
b100 %
b1110 !
#1110
b101 %
b1111 !
#1120
0$
b111 %
b0 &
b0 !
b111 "
#1130
b1110 &
b1000 %
b1 !
#1140
b1100 &
b1001 %
b10 !
#1150
b1110 &
b1010 %
b11 !
#1160
b1000 &
b1011 %
b100 !
#1170
b1110 &
b1100 %
b101 !
#1180
b1100 &
b1101 %
b110 !
#1190
b1110 &
b1110 %
b111 !
#1200
0$
b1111 %
b0 &
b1000 !
#1210
1$
b11110 &
b0 %
b1001 !
#1220
b11100 &
b1 %
b1010 !
#1230
b11110 &
b10 %
b1011 !
#1240
b11000 &
b11 %
b1100 !
#1250
b11110 &
b100 %
b1101 !
#1260
b11100 &
b101 %
b1110 !
#1270
b11110 &
b110 %
b1111 !
#1280
0$
b1000 %
b0 &
b0 !
b1000 "
#1290
b1001 %
b1 !
#1300
b1010 %
b10 !
#1310
b1011 %
b11 !
#1320
b1100 %
b100 !
#1330
b1101 %
b101 !
#1340
b1110 %
b110 !
#1350
b1111 %
b111 !
#1360
1$
b10000 &
b0 %
b1000 !
#1370
b1 %
b1001 !
#1380
b10 %
b1010 !
#1390
b11 %
b1011 !
#1400
b100 %
b1100 !
#1410
b101 %
b1101 !
#1420
b110 %
b1110 !
#1430
b111 %
b1111 !
#1440
0$
b0 &
b1001 %
b0 !
b1001 "
#1450
b10 &
b1010 %
b1 !
#1460
b1011 %
b0 &
b10 !
#1470
b110 &
b1100 %
b11 !
#1480
0$
b1101 %
b0 &
b100 !
#1490
b10 &
b1110 %
b101 !
#1500
0$
b1111 %
b0 &
b110 !
#1510
1$
b11110 &
b0 %
b111 !
#1520
b10000 &
b1 %
b1000 !
#1530
b10010 &
b10 %
b1001 !
#1540
b11 %
b10000 &
b1010 !
#1550
b10110 &
b100 %
b1011 !
#1560
b101 %
b10000 &
b1100 !
#1570
b10010 &
b110 %
b1101 !
#1580
b111 %
b10000 &
b1110 !
#1590
b11110 &
b1000 %
b1111 !
#1600
0$
b0 &
b1010 %
b0 !
b1010 "
#1610
b1011 %
b1 !
#1620
b100 &
b1100 %
b10 !
#1630
b1101 %
b11 !
#1640
0$
b1110 %
b0 &
b100 !
#1650
b1111 %
b101 !
#1660
1$
b11100 &
b0 %
b110 !
#1670
b1 %
b111 !
#1680
b10000 &
b10 %
b1000 !
#1690
b11 %
b1001 !
#1700
b10100 &
b100 %
b1010 !
#1710
b101 %
b1011 !
#1720
b110 %
b10000 &
b1100 !
#1730
b111 %
b1101 !
#1740
b11100 &
b1000 %
b1110 !
#1750
b1001 %
b1111 !
#1760
0$
b0 &
b1011 %
b0 !
b1011 "
#1770
b110 &
b1100 %
b1 !
#1780
b100 &
b1101 %
b10 !
#1790
b110 &
b1110 %
b11 !
#1800
0$
b1111 %
b0 &
b100 !
#1810
1$
b11110 &
b0 %
b101 !
#1820
b11100 &
b1 %
b110 !
#1830
b11110 &
b10 %
b111 !
#1840
b10000 &
b11 %
b1000 !
#1850
b10110 &
b100 %
b1001 !
#1860
b10100 &
b101 %
b1010 !
#1870
b10110 &
b110 %
b1011 !
#1880
b111 %
b10000 &
b1100 !
#1890
b11110 &
b1000 %
b1101 !
#1900
b11100 &
b1001 %
b1110 !
#1910
b11110 &
b1010 %
b1111 !
#1920
0$
b0 &
b1100 %
b0 !
b1100 "
#1930
b1101 %
b1 !
#1940
b1110 %
b10 !
#1950
b1111 %
b11 !
#1960
1$
b11000 &
b0 %
b100 !
#1970
b1 %
b101 !
#1980
b10 %
b110 !
#1990
b11 %
b111 !
#2000
b10000 &
b100 %
b1000 !
#2010
b101 %
b1001 !
#2020
b110 %
b1010 !
#2030
b111 %
b1011 !
#2040
b11000 &
b1000 %
b1100 !
#2050
b1001 %
b1101 !
#2060
b1010 %
b1110 !
#2070
b1011 %
b1111 !
#2080
0$
b0 &
b1101 %
b0 !
b1101 "
#2090
b10 &
b1110 %
b1 !
#2100
0$
b1111 %
b0 &
b10 !
#2110
1$
b11110 &
b0 %
b11 !
#2120
b11000 &
b1 %
b100 !
#2130
b11010 &
b10 %
b101 !
#2140
b11 %
b11000 &
b110 !
#2150
b11110 &
b100 %
b111 !
#2160
b10000 &
b101 %
b1000 !
#2170
b10010 &
b110 %
b1001 !
#2180
b111 %
b10000 &
b1010 !
#2190
b11110 &
b1000 %
b1011 !
#2200
b11000 &
b1001 %
b1100 !
#2210
b11010 &
b1010 %
b1101 !
#2220
b1011 %
b11000 &
b1110 !
#2230
b11110 &
b1100 %
b1111 !
#2240
0$
b0 &
b1110 %
b0 !
b1110 "
#2250
b1111 %
b1 !
#2260
1$
b11100 &
b0 %
b10 !
#2270
b1 %
b11 !
#2280
b11000 &
b10 %
b100 !
#2290
b11 %
b101 !
#2300
b11100 &
b100 %
b110 !
#2310
b101 %
b111 !
#2320
b10000 &
b110 %
b1000 !
#2330
b111 %
b1001 !
#2340
b11100 &
b1000 %
b1010 !
#2350
b1001 %
b1011 !
#2360
b11000 &
b1010 %
b1100 !
#2370
b1011 %
b1101 !
#2380
b11100 &
b1100 %
b1110 !
#2390
b1101 %
b1111 !
#2400
0$
b0 &
b1111 %
b0 !
b1111 "
#2410
1$
b11110 &
b0 %
b1 !
#2420
b11100 &
b1 %
b10 !
#2430
b11110 &
b10 %
b11 !
#2440
b11000 &
b11 %
b100 !
#2450
b11110 &
b100 %
b101 !
#2460
b11100 &
b101 %
b110 !
#2470
b11110 &
b110 %
b111 !
#2480
b10000 &
b111 %
b1000 !
#2490
b11110 &
b1000 %
b1001 !
#2500
b11100 &
b1001 %
b1010 !
#2510
b11110 &
b1010 %
b1011 !
#2520
b11000 &
b1011 %
b1100 !
#2530
b11110 &
b1100 %
b1101 !
#2540
b11100 &
b1101 %
b1110 !
#2550
b11110 &
b1110 %
b1111 !
#2560
b0 %
0$
b0 &
b0 !
b0 "
