fifo_mem/fifo_mem.v
module fifo_counter #(
    parameter depth = 8 // defino la profundidad del fifo que maneja
)
(
    clk,            //  Senal de reloj
    push,           //  Indica que entra un registro
    pop,            //  Indica que sale un registro
    full,           //  Indica que la memoria esta llena
    pndng,          //  Indica que hay datos sin leer
    pointer_in,     //  Puntero a donde guardar
    pointer_out,    //  Puntero a donde leer
    rst
);
    // Señales de entrada
    input clk, push, pop, rst;

    // Señales de salida
    output full, pndng;
    output reg[$clog2(depth)-1:0] pointer_out;  // Indica la posicion a leer datos

    //  Señales internas
    reg [$clog2(depth)-1:0] count;  // Indica la cantidad de registros en el FIFO

    // Defino dos maquinas de estado, una para el pointer in y otra para el pointer out
    output reg [$clog2(depth)-1:0] pointer_in;  // El estado es la posicion a guardar
    reg [$clog2(depth)-1:0] state_in;  // El estado es la posicion a guardar
    reg [$clog2(depth)-1:0] nxt_state_in;  // El estado es la posicion a guardar

    wire c;

    // Logica de siguiente estado
    addern #(.bits(depth)) nxt_state_gen (.carryin(push), .A(state_in), .B(0), .carryout(c), .S(nxt_state_in));

    // Aplico el cambio de estado
    always @(posedge clk or negedge rst) begin
        if (~rst) state_in <= 0;
        else begin
            state_in = nxt_state_in;
        end
    end

    // Logica de salida
    // Al ser una maquina de Moore, la salida depende del estado
    assign pointer_in = state_in;

endmodule

module demuxnm #(
    parameter bits = 8,     // Parametro para largo del registro
    parameter depth = 4     // Parametro para cantidad de registros
)
(
    ctrl,   // Entradas de control
    in_n,   // Entrada de N Bits
    out_nm  // M salidas de N bits
);
    input [$clog2(depth)-1:0] ctrl;         // Si tengo demux DEPTH señales preciso Log_2(DEPTH) bits de control
    input [bits-1:0] in_n;
    output [depth-1:0] [bits-1:0] out_nm ;

    // Instancio todas las salidas para mantener el control sobre estas todo el tiempo
    genvar index;
    generate
        for (index = 0; index < depth; index = index + 1) begin
            assign out_nm[index] = (ctrl == index)? in_n : 'bz;
        end
    endgenerate

endmodule

module muxnm #(
    parameter bits = 8,     // Parametro para largo del registro
    parameter depth = 4     // Parametro para cantidad de registros
)
(
    ctrl,   // Entradas de control
    in_nm,  // M entradas de N bits
    out_n   // Salida de N bits
);

    input [$clog2(depth)-1:0] ctrl; // Si debo demux DEPTH señales preciso Log_2(DEPTH) bits de control
    input [depth-1:0] [bits-1:0] in_nm ;
    output [bits-1:0] out_n;

    // A la salida tengo la entrada correspondiente al valor de ctrl
    assign out_n = in_nm[ctrl];

endmodule

// Arreglo de N Flip-Flops tipo D
module d_ff_n #(
    parameter bits = 8  // Parametro para largo del registro
)
(
    clk,      // Señal de clock
    Din_n,    // Datos de entrada de largo n
    Dout_n,   // Datos de salida de largo n
    clr
);
    input clk, clr;
    input [bits-1:0] Din_n;

    output reg [bits-1:0] Dout_n;

    always @(posedge clk or negedge clr) begin // Siempre que recibo un flanco de clk
        if (!clr) begin
            Dout_n <= 0;
        end
        else begin
            Dout_n <= Din_n;
        end
    end

endmodule

module fifo #(
    parameter bits = 8,
    parameter depth = 4
)
(
    clk,
    Din,
    Dout,
    push,
    pop,
    full,
    pndng,
    rst
);
    input clk, push, pop, rst;
    input [bits-1:0] Din;

    output full, pndng;
    output [bits-1:0] Dout;

    reg count;

    wire [$clog2(depth)-1:0] pointer_in;
    wire [$clog2(depth)-1:0] pointer_out;
    wire [bits-1:0] out_nm_mux [depth-1:0];
    wire [bits-1:0] in_nm_demux [depth-1:0];

    // fifo_counter #(depth) U1(
    //     .push(push), 
    //     .pop(pop), 
    //     .pointer_in(pointer_in), 
    //     .pointer_out(pointer_out), 
    //     .rst(rst), 
    //     .full(full), 
    //     .pndng(pndng)
    //     );
    // demuxnm #(bits, depth) U2(.ctrl(pointer_in), .in_n(Din), .out_nm(out_nm_mux));
    // d_ff_n #(bits) U3(.clk(clk), .Din_n(out_nm_mux), .Dout_n(in_nm_demux));
    // muxnm #(bits, depth) U4(.ctrl(pointer_out), .in_nm(in_nm_demux), .out_n(Dout));

endmodule

// Full-Adder
module fulladd (
    cin,    //  Carry-in
    a,      //  Bit a sumar
    b,      //  Bit a sumar
    s,      //  Suma de los bits
    cout    //  Carry-out
);
    input a, b, cin;
    output s, cout;

    // Se pueden asignar varias 'variables' separando cada asignacion con una coma en vez de punto-y-coma
    assign  s = a ^ b ^ cin,
            cout = (a & b) | (a & cin) | (b & cin);

endmodule

// En este caso se instancia n-veces un modulo por medio del bloque 'generate'
// Cada instancia del modulo 'fulladd' sera renombrado addbit[k].stage
module addern #(
    parameter bits = 4
)
(
    carryin,    // Carry-in (1-bit)
    A,          // Vector/Numero a sumar
    B,          // Vector/Numero a sumar
    S,          // Suma de los vectores/numeros
    carryout    // Carry-out (1-bit)
);
    input carryin;
    input [bits–1:0] A, B;

    output [bits–1:0] S;
    output carryout;
    
    wire [bits:0] C;    // Esta instancia sirve para unir los carrys. Tiene 1 bit mas que lo demas para el carry-out

    genvar i;   // Tipo de variable similar a integer, pero unicamente positivo y utilizable solo en bloques generate
    assign C[0] = carryin;
    assign carryout = C[bits];

    generate    // Aca instancio bit-a-bit cada sumador y realizo la suma del numero
        for (i = 0; i <= bits–1; i = i+1) begin:addbit    // Aca se renombra cada instancia
            fulladd stage (C[i], A[i], B[i], S[i], C[i+1]);
        end
    endgenerate

endmodule

Icarus/fifo_mem/d_ff_n_tb.v
// Testbench for fifos multiplexer
`timescale 1ns/100ps
`default_nettype none
`define BITS    8
`define DEPTH   4
`include "fifo_mem.v"

module d_ff_n_tb;

    reg clk_tb, clr_tb;
    reg [`BITS-1:0] Din_n_tb;
    wire [`BITS-1:0] Dout_n_tb ;

d_ff_n #(.bits(`BITS)) uut (.clk(clk_tb), .Din_n(Din_n_tb), .Dout_n(Dout_n_tb), .clr(clr_tb));

initial begin
    $dumpfile("d_ff_n_tb.vcd");
    $dumpvars(2,uut);
    $monitor("clk_tb=%d, clr=%d, Din_n_tb=%d, Dout_n_tb=%d", clk_tb, clr_tb, Din_n_tb, Dout_n_tb);
    clr_tb = 'b1;
    clk_tb = 'b0;
    Din_n_tb = 'b0;
end

always #2 clk_tb = !clk_tb;

always @(posedge clk_tb) begin

    Din_n_tb = $random%( 2**`BITS );

    if ($time > 10 && $time <= 20) begin
        clr_tb = 'b0;   // Enciendo el reset
    end
    
    if ($time > 20 && $time <= 100) begin
        clr_tb = 'b1;   // Apago el reset
    end

    if ($time > 100) begin
        $finish;        // Termino la simulacion  
    end
end
    
endmodule

// Para ejecutar la prueba se corren los siguientes comandos:
// iverilog -g2012 -o <name>.vvp <name>.v   --> Esto sintetizar el testbench y lo guarda en el archivo *.vvp
// vvp <name>.vvp                           --> Este comando efectivamente ejecuta la simulacion, crea un archivo *.vcd
// gtkwave                                  --> Ejecuta el visualizador de señales, se debe cargar el archivo *.vcd para verla

fifo_mem/d_ff_n_tb.vcd
$date
	Thu Aug 19 02:11:11 2021
$end
$version
	Icarus Verilog
$end
$timescale
	100ps
$end
$scope module d_ff_n_tb $end
$scope module uut $end
$var wire 8 ! Din_n [7:0] $end
$var wire 1 " clk $end
$var wire 1 # clr $end
$var reg 8 $ Dout_n [7:0] $end
$upscope $end
$upscope $end
$enddefinitions $end
#0
$dumpvars
bx $
1#
0"
b0 !
$end
#20
b100100 $
b100100 !
1"
#40
0"
#60
b10000001 $
b10000001 !
1"
#80
0"
#100
b1001 $
b1001 !
1"
#120
0"
#140
b0 $
0#
b1100011 !
1"
#160
0"
#180
b1101 !
1"
#200
0"
#220
b10001101 $
1#
b10001101 !
1"
#240
0"
#260
b1100101 $
b1100101 !
1"
#280
0"
#300
b10010 $
b10010 !
1"
#320
0"
#340
b1 $
b1 !
1"
#360
0"
#380
b1101 $
b1101 !
1"
#400
0"
#420
b1110110 $
b1110110 !
1"
#440
0"
#460
b111101 $
b111101 !
1"
#480
0"
#500
b11101101 $
b11101101 !
1"
#520
0"
#540
b10001100 $
b10001100 !
1"
#560
0"
#580
b11111001 $
b11111001 !
1"
#600
0"
#620
b11000110 $
b11000110 !
1"
#640
0"
#660
b11000101 $
b11000101 !
1"
#680
0"
#700
b10101010 $
b10101010 !
1"
#720
0"
#740
b11100101 $
b11100101 !
1"
#760
0"
#780
b1110111 $
b1110111 !
1"
#800
0"
#820
b10010 $
b10010 !
1"
#840
0"
#860
b10001111 $
b10001111 !
1"
#880
0"
#900
b11110010 $
b11110010 !
1"
#920
0"
#940
b11001110 $
b11001110 !
1"
#960
0"
#980
b11101000 $
b11101000 !
1"
#1000
0"
#1020
b11000101 $
b11000101 !
1"
