fifo_mem/fifo_mem.v
module fifo_counter #(
    parameter depth = 8 // defino la profundidad del fifo que maneja
)
(
    clk,            //  Senal de reloj
    push,           //  Indica que entra un registro
    pop,            //  Indica que sale un registro
    full,           //  Indica que la memoria esta llena
    pndng,          //  Indica que hay datos sin leer
    pointer_in,     //  Puntero a donde guardar
    pointer_out,    //  Puntero a donde leer
    rst
);
    // Señales de entrada
    input clk, push, pop, rst;

    // Señales de salida
    output full, pndng;
    output reg[$clog2(depth)-1:0] pointer_out;  // Indica la posicion a leer datos

    //  Señales internas
    reg [$clog2(depth)-1:0] count;  // Indica la cantidad de registros en el FIFO

    // Defino dos maquinas de estado, una para el pointer in y otra para el pointer out
    output reg [$clog2(depth)-1:0] pointer_in;  // El estado es la posicion a guardar
    reg [$clog2(depth)-1:0] state_in;  // El estado es la posicion a guardar
    reg [$clog2(depth)-1:0] nxt_state_in;  // El estado es la posicion a guardar

    wire c;

    // Logica de siguiente estado
    //addern #(.bits(depth)) nxt_state_gen (.carryin(push), .A(state_in), .B('b0), .carryout(c), .Sum(nxt_state_in));

    // Aplico el cambio de estado
    always @(posedge clk or negedge rst) begin
        if (~rst) state_in <= 0;
        else begin
            state_in = nxt_state_in;
        end
    end

    // Logica de salida
    // Al ser una maquina de Moore, la salida depende del estado
    assign pointer_in = state_in;

endmodule

module demuxnm #(
    parameter bits = 8,     // Parametro para largo del registro
    parameter depth = 4     // Parametro para cantidad de registros
)
(
    ctrl,   // Entradas de control
    in_n,   // Entrada de N Bits
    out_nm  // M salidas de N bits
);
    input [$clog2(depth)-1:0] ctrl;         // Si tengo demux DEPTH señales preciso Log_2(DEPTH) bits de control
    input [bits-1:0] in_n;
    output [depth-1:0] [bits-1:0] out_nm ;

    // Instancio todas las salidas para mantener el control sobre estas todo el tiempo
    genvar index;
    generate
        for (index = 0; index < depth; index = index + 1) begin
            assign out_nm[index] = (ctrl == index)? in_n : 'bz;
        end
    endgenerate

endmodule

module muxnm #(
    parameter bits = 8,     // Parametro para largo del registro
    parameter depth = 4     // Parametro para cantidad de registros
)
(
    ctrl,   // Entradas de control
    in_nm,  // M entradas de N bits
    out_n   // Salida de N bits
);

    input [$clog2(depth)-1:0] ctrl; // Si debo demux DEPTH señales preciso Log_2(DEPTH) bits de control
    input [depth-1:0] [bits-1:0] in_nm ;
    output [bits-1:0] out_n;

    // A la salida tengo la entrada correspondiente al valor de ctrl
    assign out_n = in_nm[ctrl];

endmodule

// Arreglo de N Flip-Flops tipo D
module d_ff_n #(
    parameter bits = 8  // Parametro para largo del registro
)
(
    clk,      // Señal de clock
    Din_n,    // Datos de entrada de largo n
    Dout_n,   // Datos de salida de largo n
    clr
);
    input clk, clr;
    input [bits-1:0] Din_n;

    output reg [bits-1:0] Dout_n;

    always @(posedge clk or negedge clr) begin // Siempre que recibo un flanco de clk
        if (!clr) begin
            Dout_n <= 0;
        end
        else begin
            Dout_n <= Din_n;
        end
    end

endmodule

module fifo #(
    parameter bits = 8,
    parameter depth = 4
)
(
    clk,
    Din,
    Dout,
    push,
    pop,
    full,
    pndng,
    rst
);
    input clk, push, pop, rst;
    input [bits-1:0] Din;

    output full, pndng;
    output [bits-1:0] Dout;

    reg count;

    wire [$clog2(depth)-1:0] pointer_in;
    wire [$clog2(depth)-1:0] pointer_out;
    wire [bits-1:0] out_nm_mux [depth-1:0];
    wire [bits-1:0] in_nm_demux [depth-1:0];

    // fifo_counter #(depth) U1(
    //     .push(push), 
    //     .pop(pop), 
    //     .pointer_in(pointer_in), 
    //     .pointer_out(pointer_out), 
    //     .rst(rst), 
    //     .full(full), 
    //     .pndng(pndng)
    //     );
    // demuxnm #(bits, depth) U2(.ctrl(pointer_in), .in_n(Din), .out_nm(out_nm_mux));
    // d_ff_n #(bits) U3(.clk(clk), .Din_n(out_nm_mux), .Dout_n(in_nm_demux));
    // muxnm #(bits, depth) U4(.ctrl(pointer_out), .in_nm(in_nm_demux), .out_n(Dout));

endmodule

// Full-Adder
module fulladd (
    cin,    //  Carry-in
    a,      //  Bit a sumar
    b,      //  Bit a sumar
    s,      //  Suma de los bits
    cout    //  Carry-out
);
    input a, b, cin;
    output s, cout;

    // Se pueden asignar varias 'variables' separando cada asignacion con una coma en vez de punto-y-coma
    assign s = (a ^ b) ^ cin;
    assign cout = (b & cin) | (a & b) | (a & cin);

endmodule

// En este caso se instancia n-veces un modulo por medio del bloque 'generate'
// Cada instancia del modulo 'fulladd' sera renombrado addbit[k].stage
module addern #(
    parameter bits = 8  // Parametro para largo del registro
)
(
    carryin,    // Carry-in (1-bit)
    A,          // Vector/Numero a sumar
    B,          // Vector/Numero a sumar
    Sum,        // Suma de los vectores/numeros
    carryout    // Carry-out (1-bit)
);
    input carryin;
    input [bits-1:0] A;
    input [bits-1:0] B;

    output [bits-1:0] Sum;
    output carryout;
    
    wire [bits:0] C;    // Esta instancia sirve para unir los carrys. Tiene 1 bit mas que lo demas para el carry-out

    genvar i;   // Tipo de variable similar a integer, pero unicamente positivo y utilizable solo en bloques generate
    assign C[0] = carryin;
    assign carryout = C[bits];

    generate    // Aca instancio bit-a-bit cada sumador y realizo la suma del numero
        for (i = 0; i <= bits-1; i = i+1) begin:addbit    // Aca se renombra cada instancia
            fulladd stage (C[i], A[i], B[i], Sum[i], C[i+1]);
        end
    endgenerate

endmodule

Icarus/fifo_mem/fulladder_tb.v
// Testbench for fifos multiplexer
`timescale 1ns/100ps
`default_nettype none
`define BITS    3
`include "fifo_mem.v"

module fulladder_tb;

    reg [2:0] IN;
    reg [1:0] OUT;

    fulladd uut(.a(IN[0]), .b(IN[1]), .cin(IN[2]), .s(OUT[0]), .cout(OUT[1]));

initial begin

    $dumpfile("fulladder_tb.vcd");
    $dumpvars(2,uut);
    $monitor("(time: %1d) IN=%d a=%d, b=%d, cin=%d, s=%d, cout=%d, OUT=%d", $time, IN, IN[0], IN[1], IN[2], OUT[0], OUT[1], OUT);
    IN = 3'b000;

end

always #10 IN = IN + 3'b001;
always #80 $finish;             // Aca ya da para una vuelta de todas las combinaciones posibles

endmodule

module addern_tb;

    reg cin;
    reg [`BITS-1:0] A_number;
    reg [`BITS-1:0] B_number;
    wire [`BITS-1:0] Sum;
    wire cout;

    addern #(.bits(`BITS)) uut
    (
        .carryin(cin),    // Carry-in (1-bit)
        .A(A_number),          // Vector/Numero a sumar
        .B(B_number),          // Vector/Numero a sumar
        .Sum(Sum),        // Suma de los vectores/numeros
        .carryout(cout)    // Carry-out (1-bit)
    );

    initial begin

        $dumpfile("addern_tb.vcd");
        $dumpvars(2,uut);
        $monitor("(time: %1d) A=%d B=%d, Cin=%d, Sum=%d, Cout=%d", $time, A_number, B_number, cin, Sum, cout);
        // Inicializo las variables/Entradas
        A_number = {`BITS{1'b0}};
        B_number = {`BITS{1'b0}};
        cin = 1'b0;

    end

    always #1 A_number = A_number + { {`BITS-1{1'b0}} , 1'b1}; // Una forma un poco engorrosa pero parametrizable de sumar 1 de forma precisa
    always #9 B_number = B_number + { {`BITS-1{1'b0}} , 1'b1};
    always #81 $finish;

endmodule

fifo_mem/fulladder_tb.vcd
$date
	Mon Aug 30 23:12:45 2021
$end
$version
	Icarus Verilog
$end
$timescale
	100ps
$end
$scope module fulladder_tb $end
$scope module uut $end
$var wire 1 ! a $end
$var wire 1 " b $end
$var wire 1 # cin $end
$var wire 1 $ cout $end
$var wire 1 % s $end
$upscope $end
$upscope $end
$enddefinitions $end
#0
$dumpvars
0%
0$
0#
0"
0!
$end
#100
1%
1!
#200
0!
1"
#300
1$
0%
1!
#400
0$
1%
1#
0!
0"
#500
0%
1$
1!
#600
0!
1"
#700
1%
1!
#800
0$
0%
0#
0!
0"
